{
  "id": "06618838-7399-45c4-80d9-90066c2d8613",
  "source": "legislation",
  "path": "http://www.legislation.gov.uk/ukla/2025/1/enacted/data.htm#chunk-3",
  "title": "-",
  "created_at": "2025-12-25T21:05:56.691Z",
  "metadata": {
    "raw": "{\"ID\":\"http://www.legislation.gov.uk/id/ukla/2025/1\",\"TITLE\":\"Norwich Livestock Market Act 2025\",\"LINK (SELF)\":\"http://www.legislation.gov.uk/id/ukla/2025/1\",\"LINK\":\"http://www.legislation.gov.uk/ukla/2025/1/enacted\",\"LINK (XML)\":\"http://www.legislation.gov.uk/ukla/2025/1/enacted/data.xml\",\"LINK (RDF/XML)\":\"http://www.legislation.gov.uk/ukla/2025/1/enacted/data.rdf\",\"LINK (AKN)\":\"http://www.legislation.gov.uk/ukla/2025/1/enacted/data.akn\",\"LINK (HTML snippet)\":\"http://www.legislation.gov.uk/ukla/2025/1/enacted/data.xht\",\"LINK (Website (XHTML) Default View)\":\"http://www.legislation.gov.uk/ukla/2025/1/enacted/data.htm\",\"LINK (PDF)\":\"http://www.legislation.gov.uk/ukla/2025/1/enacted/data.pdf\",\"LINK (Table of Contents)\":\"http://www.legislation.gov.uk/ukla/2025/1/contents/enacted\",\"AUTHOR\":\"\",\"UPDATED\":\"2025-07-22T10:25:34Z\",\"PUBLISHED\":\"2025-07-21T16:03:40.103501Z\",\"DocumentMainType\":\"UnitedKingdomLocalAct\",\"YEAR\":\"2025\",\"NUMBER\":\"1\",\"ISBN\":\"'9780105508342'\",\"CreationDate\":\"2025-07-21\",\"SUMMARY\":\"An Act to make provision for the relocation of Norwich Livestock Market; and for connected purposes.\",\"\":\"\"}"
  },
  "content": "el 3 on the standard scale. &#xD; 10 Application of the Market Act (1) Nothing in sections 4 or 8 of the Market Act affects the operation of this Act and without limitation the provisions of Part II of the Market Act have effect subject to this Act. &#xD; (2) Without limitation to subsection (1) — &#xD; (a) a market held at a new site is not to be construed as being held under section 4 (1) of the Market Act ; and &#xD; (b) a relocation under this Act is not to be construed as a closure or discontinuance under section 8 of the Market Act . &#xD; Previous Next Back to top Options/Help Print Options Official printed copies Order a copy of this legislation buy now Print The Whole Act PDF The Whole Act Web page The Whole Act Legislation is available in different versions: Latest Available (revised): The latest available updated version of the legislation incorporating changes made by subsequent legislation and applied by our editorial team. Changes we have not yet applied to the text, can be found in the ‘Changes to Legislation’ area. Original (As Enacted or Made): The original version of the legislation as it stood when it was enacted or made. No changes have been applied to the text. Opening Options Different options to open legislation in order to view more content on screen at once More Resources Access essential accompanying documents and information for this legislation item from this tab. Dependent on the legislation item being viewed this may include: the original print PDF of the as enacted version that was used for the print copy lists of changes made by and/or affecting this legislation item confers power and blanket amendment details all formats of all associated documents correction slips links to related legislation and further information resources More Resources Use this menu to access essential accompanying documents and information for this legislation item. Dependent on the legislation item being viewed this may include: the original print PDF of the as enacted version that was used for the print copy correction slips Click 'View More' or select 'More Resources' tab for additional information including: lists of changes made by and/or affecting this legislation item confers power and blanket amendment details all formats of all associated documents links to related legislation and further information resources The data on this page is available in the alternative data formats listed: HTML5 alternative version HTML snippet alternative version PDF alternative version XML alternative version Akoma Ntoso alternative version HTML RDFa alternative version RDF/XML alternative version New site design Help About us Site map Accessibility Contact us Privacy notice Cookies All content is available under the Open Government Licence v3.0 except where otherwise stated . This site additionally contains content derived from EUR-Lex, reused under the terms of the Commission Decision 2011/833/EU on the reuse of documents from the EU institutions. For more information see the EUR-Lex public statement on re-use . © Crown and database right"
}