{
  "id": "0e50b347-1688-4623-a6e4-7d5faa3fb892",
  "source": "legislation",
  "path": "data/bronze/legislation/list.json",
  "title": "list.json#27183",
  "created_at": "2025-12-25T14:44:13.648Z",
  "metadata": {
    "url": "http://www.legislation.gov.uk/uksi/2020/1394/made/data.xht",
    "type": "uksi",
    "year": 2020,
    "number": null,
    "dataUrl": "http://www.legislation.gov.uk/uksi/2020/1394/made/data.akn"
  },
  "content": "{\"type\":\"uksi\",\"year\":2020,\"number\":null,\"url\":\"http://www.legislation.gov.uk/uksi/2020/1394/made/data.xht\",\"dataUrl\":\"http://www.legislation.gov.uk/uksi/2020/1394/made/data.akn\"}"
}