{
  "id": "1e7155e4-c950-4dd4-a404-526af5f9eaab",
  "source": "legislation",
  "path": "data/bronze/legislation/list.json",
  "title": "list.json#17837",
  "created_at": "2025-12-25T13:40:28.750Z",
  "metadata": {
    "url": "http://www.legislation.gov.uk/uksi/1997/1451/contents/made",
    "type": "uksi",
    "year": 1997,
    "number": 1451,
    "dataUrl": "http://www.legislation.gov.uk/uksi/1997/1451/made/data.htm"
  },
  "content": "{\"type\":\"uksi\",\"year\":1997,\"number\":1451,\"url\":\"http://www.legislation.gov.uk/uksi/1997/1451/contents/made\",\"dataUrl\":\"http://www.legislation.gov.uk/uksi/1997/1451/made/data.htm\"}"
}