{
  "id": "4f6f399d-b771-49eb-a439-2aaa2c13c86c",
  "source": "legislation",
  "path": "data/bronze/legislation/list.json",
  "title": "list.json#22837",
  "created_at": "2025-12-25T14:13:00.582Z",
  "metadata": {
    "url": "http://www.legislation.gov.uk/uksi/2008/2104/contents/made",
    "type": "uksi",
    "year": 2008,
    "number": null,
    "dataUrl": "http://www.legislation.gov.uk/uksi/2008/2104/made/data.htm"
  },
  "content": "{\"type\":\"uksi\",\"year\":2008,\"number\":null,\"url\":\"http://www.legislation.gov.uk/uksi/2008/2104/contents/made\",\"dataUrl\":\"http://www.legislation.gov.uk/uksi/2008/2104/made/data.htm\"}"
}