{
  "id": "63f7f79b-fdb0-4b44-bc85-cff237f468c9",
  "source": "legislation",
  "path": "data/bronze/legislation/list.json",
  "title": "list.json#22835",
  "created_at": "2025-12-25T14:12:59.730Z",
  "metadata": {
    "url": "http://www.legislation.gov.uk/uksi/2008/2106/contents/made",
    "type": "uksi",
    "year": 2008,
    "number": null,
    "dataUrl": "http://www.legislation.gov.uk/uksi/2008/2106/made/data.htm"
  },
  "content": "{\"type\":\"uksi\",\"year\":2008,\"number\":null,\"url\":\"http://www.legislation.gov.uk/uksi/2008/2106/contents/made\",\"dataUrl\":\"http://www.legislation.gov.uk/uksi/2008/2106/made/data.htm\"}"
}