{
  "id": "77b6bcff-1d94-4b1f-9ecd-ac9bce76c8a2",
  "source": "legislation",
  "path": "http://www.legislation.gov.uk/ukpga/2025/24/2025-10-27/data.htm#chunk-2",
  "title": "-",
  "created_at": "2025-12-25T21:05:40.604Z",
  "metadata": {
    "raw": "{\"ID\":\"http://www.legislation.gov.uk/id/ukpga/2025/24\",\"TITLE\":\"Bus Services Act 2025\",\"LINK (SELF)\":\"http://www.legislation.gov.uk/id/ukpga/2025/24\",\"LINK\":\"http://www.legislation.gov.uk/ukpga/2025/24/2025-10-27\",\"LINK (XML)\":\"http://www.legislation.gov.uk/ukpga/2025/24/2025-10-27/data.xml\",\"LINK (RDF/XML)\":\"http://www.legislation.gov.uk/ukpga/2025/24/2025-10-27/data.rdf\",\"LINK (AKN)\":\"http://www.legislation.gov.uk/ukpga/2025/24/2025-10-27/data.akn\",\"LINK (HTML snippet)\":\"http://www.legislation.gov.uk/ukpga/2025/24/2025-10-27/data.xht\",\"LINK (Website (XHTML) Default View)\":\"http://www.legislation.gov.uk/ukpga/2025/24/2025-10-27/data.htm\",\"LINK (PDF)\":\"http://www.legislation.gov.uk/ukpga/2025/24/2025-10-27/data.pdf\",\"LINK (Table of Contents)\":\"http://www.legislation.gov.uk/ukpga/2025/24/contents\",\"AUTHOR\":\"\",\"UPDATED\":\"2025-12-03T10:49:05Z\",\"PUBLISHED\":\"2025-10-29T17:44:15.572871Z\",\"DocumentMainType\":\"UnitedKingdomPublicGeneralAct\",\"YEAR\":\"2025\",\"NUMBER\":\"24\",\"ISBN\":\"'9780105702931'\",\"CreationDate\":\"2025-10-27\",\"SUMMARY\":\"An Act to make provision about local and school bus services; and for connected purposes.\",\"\":\"\"}"
  },
  "content": "Transport Act 2000 relating to a proposed franchising scheme or a variation of such a scheme, but &#xD; (b) the scheme has not been made or varied in pursuance of the consultation document. &#xD; (3) Where this subsection applies the franchising authority or authorities may, when making or varying the scheme in pursuance of the consultation document, specify a minimum period under section 123H(2)(d) or (3)(c) which is less than six months. &#xD; Commencement Information I4 S. 4 not in force at Royal Assent, see s. 41(5) 5 References to local services E+W (1) The Transport Act 2000 is amended as follows. &#xD; (2) In section 123E (4) (a) (consultation) , after “local services” insert “which have one or more stopping places” . &#xD; (3) In section 123N (2) (a) (revocation), after “local services” insert “which have one or more stopping places” . &#xD; (4) In section 123Q (5) (a) (application for service permit), after “local services” insert “which have one or more stopping places” . &#xD; (5) In section 123R (5) (a) (conditions), after “local services” insert “which have one or more stopping places” . &#xD; Commencement Information I5 S. 5 not in force at Royal Assent, see s. 41(5) Prospective Franchising schemes: non-franchised services E+W 6 Criteria for granting service permits E+W (1) Section 123Q of the Transport Act 2000 (application for service permit) is amended in accordance with subsections (2) to (4) . &#xD; (2) After subsection (5) insert— &#xD; “ (5A) If the application is for a service permit for a cross-boundary service, the authority or authorities may grant the permit applied for if they are satisfied that— &#xD; (a) the benefits to persons making journeys on the proposed service will outweigh any adverse effect on any local service that is provided under a local service contract in the area to which the scheme relates, or &#xD; (b) the benefits of the proposed service to the economy of the relevant area, or to persons living in that area, will outweigh any such adverse effect. &#xD; (5B) If the application is for a service permit for a service that is not a cross-boundary service, the authority or authorities may grant the permit applied for if they are satisfied that the benefits of the proposed service to the economy of the area to which the scheme relates, or to persons living in that area, will outweigh any adverse effect on any local service that is provided under a local service contract in that area. ” &#xD; (3) In subsection (6) , for “if they are not satisfied as to the matters in subsection (5)(a) and (b)” substitute “except under subsection (5), (5A) or (5B) ” . &#xD; (4) After subsection (7) insert— &#xD; “ (8) In this section— &#xD; “ cross-boundary service ”, in relation to a franchising scheme, means a service that— &#xD; (a) has one or more stopping places in the area to which the scheme relates, and &#xD; (b) has one or more stopping places outside that area; &#xD; “ relevant area ”, in relation to a cross-boundary service, means the combined area of each— &#xD; (a) local transport authority, &#xD; (b) council in Scotland, and &#xD; (c) Transport Partnership created under the Transport (Scotland) Act 2005 , &#xD; in which the service has a stopping place. ” &#xD; (5) In section 123S (2) of that Act (revocation and suspension)— &#xD; (a) in paragraph (a) , for “that a matter in section 123Q(5)(a) or (b)” substitute “if the permit was granted under subsection (5) of section 123Q, that a matter in paragraph (a) or (b) of that subsection” ; &#xD; (b) after that paragraph insert— &#xD; “ (aa) if the permit was granted under subsection (5A) or (5B) of that section, that the authority or authorities are no longer satisfied as mentioned in the subsection in question, ” . &#xD; (6) The amendments made by this section apply only in relation to applications for a service permit made on or after the date on which this section comes into force. &#xD; Commencement Information I6 S. 6 not in force at Royal Assent, see s. 41(5) 7 Registration of services provided under service permits E+W (1) The Transport Act 2000 is amended as follows. &#xD; (2) In section 123J (effect of local service contracts: registration requirements and provision of services), after subsection (4) insert— &#xD; “ (4A) Subsection (2) does not apply in relation to a local service which is provided under a service permit. ” &#xD; (3) In section 123P (service permits), after subsection (2) insert— &#xD; “ (3) The authority or authorities must inform a traffic commissioner of the grant of a service permit under this section. ” &#xD; (4) After section 123P insert— &#xD; “ 123PA Registration exemption for services provided under service permits (1) The franchising authority operating a franchising scheme, or the franchising authorities operating such a scheme acting jointly, may grant an exemption from registration in respect of any local service which is, or class of local services which are, provided under a service permit in the area to which the scheme relates. &#xD; (2) Where such an exemption has effect, sections 6 to 9 of the Transport Act 1985 (registration of local services) do not have effect in relation to the service, or class of services, so far as operated in that area. &#xD; (3) The franchising authority or authorities may vary or revoke an exemption granted by them under this section. &#xD; (4) Where an exemption is granted, varied or revoked under this section, the franchising authority or authorities must— &#xD; (a) publish, in such manner as they think fit, details of the grant, variation or revocation of the exemption, and &#xD; (b) before the end of the period of 14 days beginning with the day on which the exemption is granted, varied or revoked, inform a traffic commissioner of the grant, variation or revocation of the exemption. ” &#xD; (5) In section 123S (revocation and suspension), after subsection (2) insert— &#xD; “ (2A) The franchising authority or authorities must inform a traffic commissioner of the revocation or suspension of a service permit under this section. ” &#xD; (6) In section 123V (1) (transitional provision about schemes), after paragraph (b) insert— &#xD; “ (ba) the application of section 123PA in relation to services or classes of services (registration exemption for services provided under service permits), ” . &#xD; Commencement Information I7 S. 7 not in force at Royal Assent, see s. 41(5) 8 Substitute road services E+W (1) Section 123J of the Transport Act 2000 (effect of local service contracts: registration requirements and provision of services) is amended as follows. &#xD; (2) In subsection (5) — &#xD; (a) omit the “or” at the end of paragraph (a) ; &#xD; (b) at the end of paragraph (b) insert “ , or &#xD; (c) a service falling within subsection (8). ” &#xD; (3) After subsection (7) insert— &#xD; “ (8) A service falls within this subsection if it is a local service provided under an agreement entered into, where a service for the carriage of passengers by railway or tramway has been temporarily interrupted— &#xD; (a) under section 40 of the Railways Act 2005 (substitute road services), or &#xD; (b) with the person who usually provides the railway or tramway service. ” &#xD; Commencement Information I8 S. 8 not in force at Royal Assent, see s. 41(5) Prospective Franchising schemes: procedure E+W 9 Report on assessment of proposed scheme E+W (1) Section 123D of the Transport Act 2000 (audit) is amended in accordance with subsections (2) to (8) . &#xD; (2) For subsection (1) substitute— &#xD; “ (1) A franchising authority, or two or more franchising authorities acting jointly, may not proceed with a proposed franchising scheme unless they have obtained a report from an independent approved person on the assessment of the proposed scheme (see section 123B). ” &#xD; (3) In subsection (2) — &#xD; (a) omit “auditor’s”; &#xD; (b) for “auditor” substitute “approved person” ; &#xD; (c) in paragraph (a), for “123B(3)(d) or"
}