{
  "id": "81b70905-837e-4a91-a2ca-785fd5c3d73d",
  "source": "legislation",
  "path": "data/bronze/legislation/list.json",
  "title": "list.json#8649",
  "created_at": "2025-12-25T12:43:58.409Z",
  "metadata": {
    "url": "http://www.legislation.gov.uk/uksi/1968/1604/contents/made",
    "type": "uksi",
    "year": 1968,
    "number": 1604,
    "dataUrl": null
  },
  "content": "{\"type\":\"uksi\",\"year\":1968,\"number\":1604,\"url\":\"http://www.legislation.gov.uk/uksi/1968/1604/contents/made\",\"dataUrl\":null}"
}