{
  "id": "875325c8-e9f2-4ebc-852e-14798d003a90",
  "source": "legislation",
  "path": "data/bronze/legislation/list.json",
  "title": "list.json#14030",
  "created_at": "2025-12-25T13:16:49.160Z",
  "metadata": {
    "url": "http://www.legislation.gov.uk/uksi/1988/2099/contents/made",
    "type": "uksi",
    "year": 1988,
    "number": 2099,
    "dataUrl": "http://www.legislation.gov.uk/uksi/1988/2099/made/data.htm"
  },
  "content": "{\"type\":\"uksi\",\"year\":1988,\"number\":2099,\"url\":\"http://www.legislation.gov.uk/uksi/1988/2099/contents/made\",\"dataUrl\":\"http://www.legislation.gov.uk/uksi/1988/2099/made/data.htm\"}"
}