{
  "id": "9afc2a2a-6b83-46b3-a748-455039dc34ba",
  "source": "legislation",
  "path": "http://www.legislation.gov.uk/ukpga/2025/21/2025-12-12/data.htm#chunk-1",
  "title": "-",
  "created_at": "2025-12-25T21:05:43.475Z",
  "metadata": {
    "raw": "{\"ID\":\"http://www.legislation.gov.uk/id/ukpga/2025/21\",\"TITLE\":\"Football Governance Act 2025\",\"LINK (SELF)\":\"http://www.legislation.gov.uk/id/ukpga/2025/21\",\"LINK\":\"http://www.legislation.gov.uk/ukpga/2025/21/2025-12-12\",\"LINK (XML)\":\"http://www.legislation.gov.uk/ukpga/2025/21/2025-12-12/data.xml\",\"LINK (RDF/XML)\":\"http://www.legislation.gov.uk/ukpga/2025/21/2025-12-12/data.rdf\",\"LINK (AKN)\":\"http://www.legislation.gov.uk/ukpga/2025/21/2025-12-12/data.akn\",\"LINK (HTML snippet)\":\"http://www.legislation.gov.uk/ukpga/2025/21/2025-12-12/data.xht\",\"LINK (Website (XHTML) Default View)\":\"http://www.legislation.gov.uk/ukpga/2025/21/2025-12-12/data.htm\",\"LINK (PDF)\":\"http://www.legislation.gov.uk/ukpga/2025/21/2025-12-12/data.pdf\",\"LINK (Table of Contents)\":\"http://www.legislation.gov.uk/ukpga/2025/21/contents\",\"AUTHOR\":\"\",\"UPDATED\":\"2025-12-18T12:01:30Z\",\"PUBLISHED\":\"2025-07-22T12:41:59.376632Z\",\"DocumentMainType\":\"UnitedKingdomPublicGeneralAct\",\"YEAR\":\"2025\",\"NUMBER\":\"21\",\"ISBN\":\"'9780105702894'\",\"CreationDate\":\"2025-07-21\",\"SUMMARY\":\"An Act to establish the Independent Football Regulator; to make provision for the licensing of football clubs; to make provision about the distribution of revenue received by organisers of football competitions; and for connected purposes.\",\"\":\"\"}"
  },
  "content": "Football Governance Act 2025 Skip to main content Skip to navigation legislation.gov.uk https://www.nationalarchives.gov.uk Cymraeg Home Explore our collections Research tools Help and guidance What's new About us Search Legislation Search Legislation Title: (or keywords in the title) Year: Number: Type: All UK Legislation (excluding originating from the EU) -------------------------------------------- All Legislation (including originating from the EU) -------------------------------------------- All Primary Legislation UK Public General Acts UK Local Acts UK Private and Personal Acts Acts of the Scottish Parliament Acts of Senedd Cymru Acts of the National Assembly for Wales Measures of the National Assembly for Wales Church Measures Acts of the Northern Ireland Assembly Acts of the Old Scottish Parliament Acts of the English Parliament Acts of the Old Irish Parliament Acts of the Parliament of Great Britain Local Acts of the Parliament of Great Britain Private and Personal Acts of the Parliament of Great Britain Northern Ireland Orders in Council Measures of the Northern Ireland Assembly Acts of the Northern Ireland Parliament -------------------------------------------- All Secondary Legislation UK Statutory Instruments Welsh Statutory Instruments Scottish Statutory Instruments Northern Ireland Statutory Rules Church Instruments UK Ministerial Directions UK Ministerial Orders UK Statutory Rules and Orders Northern Ireland Statutory Rules and Orders -------------------------------------------- All Legislation originating from the EU Regulations originating from the EU Decisions originating from the EU Directives originating from the EU European Union Treaties -------------------------------------------- All Draft Legislation UK Draft Statutory Instruments Scottish Draft Statutory Instruments Northern Ireland Draft Statutory Rules -------------------------------------------- All Impact Assessments UK Impact Assessments Search Advanced Search Football Governance Act 2025 You are here: UK Public General Acts 2025 c. 21 Whole Act Table of Contents Content More Resources Previous Next Plain View Print Options What Version Latest available (Revised) Point in Time (12/12/2025) Original (As enacted) Advanced Features Show Geographical Extent (e.g. E ngland, W ales, S cotland and N orthern I reland) Show Timeline of Changes Opening Options Open whole Act Open Act without Schedules Open Schedules only More Resources Original: King's Printer Version View more Changes over time for: Football Governance Act 2025 Alternative versions: 21/07/2025 - Amendment 01/11/2025 - Amendment 12/12/2025 - Amendment 12/12/2025 Point in time Status: Point in time view as at 12/12/2025. Changes to legislation: There are currently no known outstanding effects for the Football Governance Act 2025. Changes to Legislation Revised legislation carried on this site may not be fully up to date. At the current time any known changes or effects made by subsequent legislation have been applied to the text of the legislation you are viewing by the editorial team. Please see ‘Frequently Asked Questions’ for details regarding the timescales for which new effects are identified and recorded on this site. Football Governance Act 2025 2025 CHAPTER 21 An Act to establish the Independent Football Regulator; to make provision for the licensing of football clubs; to make provision about the distribution of revenue received by organisers of football competitions; and for connected purposes. [21st July 2025] B e it enacted by the King’s most Excellent Majesty, by and with the advice and consent of the Lords Spiritual and Temporal, and Commons, in this present Parliament assembled, and by the authority of the same, as follows:—&#xD; Part 1 E+W Purpose, overview and key definitions 1 Purpose and overview E+W (1) The purpose of this Act is to protect and promote the sustainability of English football. &#xD; (2) For that purpose— &#xD; (a) Part 2 establishes the Independent Football Regulator (referred to in this Act as “ the IFR ”) and makes provision about the exercise of its functions; &#xD; (b) Part 3 makes provision for the IFR to grant operating licences to football clubs; &#xD; (c) Part 4 provides for the IFR to make determinations about whether persons are suitable to be owners or officers of football clubs; &#xD; (d) Part 5 imposes various duties on football clubs, the owners and officers of football clubs and the organisers of football competitions; &#xD; (e) Part 6 provides a mechanism whereby the IFR can make an order requiring the organiser of a football competition to distribute revenue received by that organiser; &#xD; (f) Parts 7 and 8 make provision about the investigation and enforcement powers of the IFR; &#xD; (g) Part 9 makes provision about reviews of and appeals from decisions of the IFR; &#xD; (h) Part 10 makes general provision, including about the disclosure of information by and to the IFR. &#xD; (3) For the purposes of this section, English football is sustainable if it— &#xD; (a) continues to serve the interests of fans of regulated clubs, and &#xD; (b) continues to contribute to the economic or social well-being of the local communities with which regulated clubs are associated. &#xD; (4) For the meanings of “English football”, “regulated club” and for other key terms used in this Act, see section 2 . &#xD; Commencement Information I1 S. 1 in force at Royal Assent, see s. 100(2)(a) 2 Key definitions E+W (1) In this Act— &#xD; “ club ” or “ football club ” means a body that operates a team;&#xD; “ competition ”, in relation to football, means a league (or a division of a league), a cup, a tournament or any other competition;&#xD; “ competition organiser ” means a body that organises a competition;&#xD; “ English football ” means all regulated clubs and all specified competitions, taken together;&#xD; “ football ” means association football;&#xD; “ the IFR ” means the Independent Football Regulator;&#xD; “ licensed club ” means a club that holds an operating licence;&#xD; “ operating licence ” means a provisional operating licence or a full operating licence (see section 15 );&#xD; “ regulated club ” means a club that operates a relevant team (whether or not the club is a licensed club);&#xD; “ relevant team ” means a team that is entered into, is a member of, or participates in a specified competition;&#xD; “ specified competition ” means a competition specified in regulations under subsection (3) ;&#xD; “ specified competition organiser ” means a body that organises a specified competition;&#xD; “ team ” means a football team.&#xD; (2) For the purposes of this Act, a club “operates” a team if it is responsible for the team’s entry into, membership of, or participation in a competition. &#xD; (3) The Secretary of State may by regulations specify a competition; but the Secretary of State may not specify a competition unless the teams that are entered into it, or that are members of it, or that participate in it are exclusively or predominantly English teams. &#xD; (4) For the purposes of subsection (3) , a team is an “English team” if the ground at which the team customarily plays its home matches is in England. &#xD; (5) Before making regulations under subsection (3) the Secretary of State— &#xD; (a) must assess whether it would be appropriate to exercise the power and, if so, how, &#xD; (b) in carrying out the assessment, must consult— &#xD; (i) the IFR, &#xD; (ii) the Football Association, and &#xD; (iii) any other persons the Secretary of State considers appropriate, and &#xD; (c) must publish and lay before Parliament a report on the outcome of the assessment. &#xD; (6) Subsection (5) does not apply in respect of the first regulations made under subsection (3) . &#xD; (7) Sections 3 , 4 , 26 , 56 , 67 and 92 define other terms used in this Act. &#xD; Commencement Information I2 S. 2 in force at Royal Assent, see s. 100(2)(a) 3 Meaning of “owner” etc E+W (1) In this Act"
}