{
  "id": "af6c96d2-c308-4229-a076-b967d93ae649",
  "source": "legislation",
  "path": "data/bronze/legislation/list.json",
  "title": "list.json#1341",
  "created_at": "2025-12-25T11:59:30.073Z",
  "metadata": {
    "url": "http://www.legislation.gov.uk/ukpga/Geo5/15-16/44/contents/enacted",
    "type": "ukpga",
    "year": 1925,
    "number": 44,
    "dataUrl": null
  },
  "content": "{\"type\":\"ukpga\",\"year\":1925,\"number\":44,\"url\":\"http://www.legislation.gov.uk/ukpga/Geo5/15-16/44/contents/enacted\",\"dataUrl\":null}"
}