{
  "id": "bcc7255c-8a2e-42fc-bf60-4cec05ec65eb",
  "source": "legislation",
  "path": "data/bronze/legislation/list.json",
  "title": "list.json#457",
  "created_at": "2025-12-25T11:53:57.452Z",
  "metadata": {
    "url": "http://www.legislation.gov.uk/ukpga/Geo5/1-2/54/contents/enacted",
    "type": "ukpga",
    "year": 1911,
    "number": 54,
    "dataUrl": null
  },
  "content": "{\"type\":\"ukpga\",\"year\":1911,\"number\":54,\"url\":\"http://www.legislation.gov.uk/ukpga/Geo5/1-2/54/contents/enacted\",\"dataUrl\":null}"
}