{
  "id": "c7833352-e7b2-4a2a-a327-fc16d39ef0ed",
  "source": "legislation",
  "path": "data/bronze/legislation/list.json",
  "title": "list.json#8979",
  "created_at": "2025-12-25T12:45:43.609Z",
  "metadata": {
    "url": "http://www.legislation.gov.uk/uksi/1971/2162/contents/made",
    "type": "uksi",
    "year": 1971,
    "number": 2162,
    "dataUrl": null
  },
  "content": "{\"type\":\"uksi\",\"year\":1971,\"number\":2162,\"url\":\"http://www.legislation.gov.uk/uksi/1971/2162/contents/made\",\"dataUrl\":null}"
}