{
  "id": "c91179aa-2693-4e6e-b637-1ee47fd47ffb",
  "source": "legislation",
  "path": "data/bronze/legislation/list.json",
  "title": "list.json#18223",
  "created_at": "2025-12-25T13:43:01.310Z",
  "metadata": {
    "url": "http://www.legislation.gov.uk/uksi/1997/812/contents/made",
    "type": "uksi",
    "year": 1997,
    "number": 812,
    "dataUrl": "http://www.legislation.gov.uk/uksi/1997/812/made/data.htm"
  },
  "content": "{\"type\":\"uksi\",\"year\":1997,\"number\":812,\"url\":\"http://www.legislation.gov.uk/uksi/1997/812/contents/made\",\"dataUrl\":\"http://www.legislation.gov.uk/uksi/1997/812/made/data.htm\"}"
}