{
  "id": "cc8c1fb0-c3f1-406c-9cc5-20b388bdb910",
  "source": "legislation",
  "path": "data/bronze/legislation/list.json",
  "title": "list.json#24726",
  "created_at": "2025-12-25T14:26:40.677Z",
  "metadata": {
    "url": "http://www.legislation.gov.uk/wsi/2015/1551/contents/made",
    "type": "uksi",
    "year": 2015,
    "number": 1551,
    "dataUrl": null
  },
  "content": "{\"type\":\"uksi\",\"year\":2015,\"number\":1551,\"url\":\"http://www.legislation.gov.uk/wsi/2015/1551/contents/made\",\"dataUrl\":null}"
}