{
  "id": "d3a240b2-a672-4c60-b989-86b6a2202c85",
  "source": "legislation",
  "path": "data/bronze/legislation/list.json",
  "title": "list.json#31070",
  "created_at": "2025-12-25T15:16:58.773Z",
  "metadata": {
    "url": "http://www.legislation.gov.uk/uksi/2024/402/2025-07-17/data.xht",
    "type": "uksi",
    "year": 2024,
    "number": null,
    "dataUrl": "http://www.legislation.gov.uk/uksi/2024/402/2025-07-17/data.akn"
  },
  "content": "{\"type\":\"uksi\",\"year\":2024,\"number\":null,\"url\":\"http://www.legislation.gov.uk/uksi/2024/402/2025-07-17/data.xht\",\"dataUrl\":\"http://www.legislation.gov.uk/uksi/2024/402/2025-07-17/data.akn\"}"
}