{
  "id": "e7ca599a-fad4-4779-b549-9e05f3353347",
  "source": "legislation",
  "path": "data/bronze/legislation/list.json",
  "title": "list.json#5913",
  "created_at": "2025-12-25T12:27:37.616Z",
  "metadata": {
    "url": "http://www.legislation.gov.uk/ukpga/2003/34/contents",
    "type": "ukpga",
    "year": 2003,
    "number": 34,
    "dataUrl": "http://www.legislation.gov.uk/ukpga/2003/34/2003-11-13/data.htm"
  },
  "content": "{\"type\":\"ukpga\",\"year\":2003,\"number\":34,\"url\":\"http://www.legislation.gov.uk/ukpga/2003/34/contents\",\"dataUrl\":\"http://www.legislation.gov.uk/ukpga/2003/34/2003-11-13/data.htm\"}"
}