{
  "id": "ebdccafa-6445-47ec-9857-c8e52d09502b",
  "source": "legislation",
  "path": "data/bronze/legislation/list.json",
  "title": "list.json#622",
  "created_at": "2025-12-25T11:54:58.770Z",
  "metadata": {
    "url": "http://www.legislation.gov.uk/ukpga/Geo5/4-5/28/contents/enacted",
    "type": "ukpga",
    "year": 1914,
    "number": 28,
    "dataUrl": null
  },
  "content": "{\"type\":\"ukpga\",\"year\":1914,\"number\":28,\"url\":\"http://www.legislation.gov.uk/ukpga/Geo5/4-5/28/contents/enacted\",\"dataUrl\":null}"
}