{
  "id": "c723ed8a-3bc0-4a95-baf7-d632aeb65abb",
  "source": "justice-gov-uk",
  "path": "data/bronze/justice-gov-uk/www_justice_gov_uk_courts_procedure_rules_civil_rules_county_court_closures.html",
  "title": "www_justice_gov_uk_courts_procedure_rules_civil_rules_county_court_closures.html",
  "created_at": "2025-12-25T15:25:35.957Z",
  "metadata": {},
  "content": "PRACTICE DIRECTION &#8211; COUNTY COURT CLOSURES &#8211; Civil Procedure Rules &#8211; Justice UK Cookie Settings Are you OK with cookies? We use small files called ‘cookies’ on www.justice.gov.uk. Some are essential to make the site work, some help us to understand how we can improve your experience, and some are set by third parties. You can choose to turn off the non-essential cookies. Which cookies are you happy for us to use? I am OK with cookies Only use essential cookies Choose which cookies we use Close Choose which cookies we use Marketing cookies Off On Google Analytics Off On We use Google Analytics to measure how you use the website so we can improve it based on user needs. We do not allow Google Analytics to use or share the data about how you use this site. See our Google Analytics cookies Google Analytics Name Purpose Expires _ga These help us count how many people visit justice.gov.uk by tracking if you’ve visited before 2 years _gid These help us count how many people visit justice.gov.uk by tracking if you’ve visited before 24 hours _gat These help us to manage how we collect analytics when we have lots of visitors on the site at one time 10 minutes Google Analytics Events Off On We use Google Analytics events to measure clicks within the pages and extended usage of the site See our Google Analytics Events cookies Google Analytics Events Name Purpose Expires _ga These help us count how many people visit justice.gov.uk by tracking if you’ve visited before 2 years Essential cookies Always on All users These cookies will always need to be on because they make our site work. See our All users cookies All users Name Purpose Expires wordpress_test_cookie This is used to test whether the browser accepts cookies When you close your browser PHPSESSID This is used to link your device to the information sent to the server from your browser. It is typically used to avoid you having to retype information when moving from one page to another. When you close your browser ccfw-banner-hidden Lets us know you have chosen which cookies are used so we can stop the cookie banner appearing when you return to the site. 1 year ccfw-gtm-allowed Lets us know you have accepted certain cookies so we can stop them loading when you return to the site. 1 year ccfw-time This is used to store the cookie expiry dates so we know when to ask you again for consent. 1 year ccfw_gtm_id This cookie is used to link the cookie consent banner to Google Tag Manager 1 year Logged in users These cookies apply when users log in. They will always be on because they make our site work. See our Logged in users cookies Logged in users Name Purpose Expires wordpress_[hash] This authenticates you when you log in to the admin area When you close your browser wordpress_logged_in This shows the site that you’re logged in and who you are so you can access the functions you need When you close your browser wordpress_sec If you are logged in as a site admin, this stores your authentication details. When you close your browser wp-settings-{time}-[UID] The number on the end [UID] is your individual user ID from the users database. 1 year > Save cookie preferences . Home &nbsp; Courts Procedure rules Offenders Search Courts Procedure rules Civil Rules & Practice Directions PRACTICE DIRECTION – COUNTY COURT CLOSURES Home » Courts » Procedure rules » Civil » Rules & Practice Directions » PRACTICE DIRECTION – COUNTY COURT CLOSURES Menu ≡ PRACTICE DIRECTION – COUNTY COURT CLOSURES PRACTICE DIRECTION – COUNTY COURT CLOSURES Contents of this Practice Direction Title Number Scope and Interpretation Para.&nbsp;1.1 Transfer of Work Para.&nbsp;2.1 ANNEX &nbsp; Scope and Interpretation 1.1 This Practice Direction prescribes the procedure for the transfer of work from a county court prior to its closure. 1.2 In this Practice Direction – ‘closing court’ means a court which is subject to closure; and ‘recipient court’ means a court or courts to which work from the closing court is to be transferred in accordance with paragraphs 2.1 &#8211; 2.5. Transfer of Work 2.1 If a court is to be closed, work shall be transferred to the recipient court which has been identified in directions made by the Lord Chancellor, under section 2 of the County Courts Act 1984, having consulted the Lord Chief Justice and, where necessary, following consultation between the Lord Chief Justice and the Master of the Rolls, Chancellor of the High Court or the President of the Family Division. 2.2 The transfer of work shall, so far as possible and subject to any direction of a judge in any particular case, be in accordance with the annexed schedules, namely: ‘Schedule 1 &#8211; Civil Proceedings (generally)’, ‘Schedule 2 &#8211; Family Proceedings’ and ‘Schedule 3 &#8211; Insolvency Proceedings’ (‘the schedules’). 2.3 Any case falling outside the categories of work listed in the schedules will be referred to a judge in the closing court for determination of the appropriate recipient court. 2.4 If a case is transferred from the closing court to a recipient court by an order made under rule 3.3(4) of the Civil Procedure Rules or rule 4.3(4) of the Family Procedure Rules, the closing court shall notify all parties that they may apply to the recipient court, on notice and within 7 days of the date of service of the transfer order, to vary the court to which the case should be transferred. 2.5 On the date that a court closes, all work which has not previously been transferred from that court shall be transferred to the recipient court or courts in accordance with paragraph 2.1. ANNEX Schedule 1 – Civil Proceedings (generally) Key Court Court A Closing Court Court B Recipient Court. There may be more than one recipient court. Number Timing (period prior to closure) Procedure Action (subject to any direction of a judge in accordance with paragraph 2.2 of the Practice Direction) 1.1 3 months Request to issue a Part 7 claim at Court A Transfer to and issue in the name of Court B 1.2 3 months Cases transferred to Court A on receipt of a defence from a defendant Case to remain at Court A for directions under CPR Part 26 1.3 3 months Requirement to list a case/application for date post-closure Transfer proceedings to Court B for that court to list for hearing 2 2 months Request to issue Part 8 claim at Court A (including claim for possession under Part 55) Issue the case at Court A but transfer proceedings to Court B for that court to list for hearing 3.1 6 weeks Request to issue or re-issue warrant of execution (including possession warrants not issued through PCOL) where Court A is the home court Transfer warrant to Court B for execution 3.2 6 weeks Receipt of a foreign warrant (electronic) Before printing – update executing field to ‘Court B’ (where it will then be executed as a foreign warrant) 3.3 6 weeks Receipt of foreign warrant (paper) Forward to Court B for manual input and execution 3.4 6 weeks Receipt of possession warrants from PCOL Update executing field to ‘Court B’. This will create a final return – warrants should then be entered as a foreign warrant at Court B 4 2 months (or when lists become full, whichever is the sooner) Receipt of enforcement process that requires a hearing, including applications for an order to obtain information from judgment debtors Transfer proceedings to Court B for that court to list for hearing 5 2 months Consolidated orders Transfer to Court B following payment of dividend Schedule 2 – Family Proceedings Key Court Court A Closing Court Court B Recipient Court. There may be more than one recipient court. Number Timing (months prior to closure) Procedure Action (subject to any direction of a judge in accordance with paragraph 2.2 of the Practice Direction) 1.1 3 months Request to issue new family proceedings To be forwarded to and issued in the name of Court B 1.2 3 months Request to issue applications within existing family proceedings Transfer proceedings to Court B for that court to list for hearing Schedule 3 – Insolvency Proceedings Key Court Court A Closing Court Court B Recipient Court. There may be more than one recipient court. Number Timing (months prior to closure) Procedure Action (subject to any direction of a judge in accordance with paragraph 2.2 of the Practice Direction) 1.1 2 months (or when lists become full which ever is the sooner) Insolvency – creditors petitions Transfer proceedings to Court B for that court to list for hearing 1.2 2 months (or when lists become full, whichever is the sooner) Insolvency – winding up petitions (High Court) Transfer proceedings to Court B for that court to list for hearing 1.3 2 months (or when lists become full which ever is the sooner) Insolvency – statutory demands Transfer proceedings to Court B for that court to list for hearing (should judicial practice be to list for hearing) 1.4 2 months (or when lists become full which ever is the sooner) Insolvency – company voluntary arrangements Transfer proceedings to Court B for that court to list for hearing (should judicial practice be to list for hearing) 1.5 2 months (or when lists become full which ever is the sooner) Insolvency – transfers in from other county courts Transfer to Court B 1.6 2 months (or when lists become full which ever is the sooner) Insolvency – applications Transfer proceedings to Court B for that court to list for hearing (should a hearing be necessary) Updated: Monday, 30 January 2017 Top ↑ Home Courts Courts Procedure rules Civil Rules & Practice Directions PRACTICE DIRECTION – COUNTY COURT CLOSURES Accessibility Cookies Contacts Copyright Help Privacy Webchats Website queries Citizen and business advice GOV UK For citizen and business advice on justice, rights and more visit GOV.UK © Crown copyright"
}